codesum/__init__.py
codesum/app.py
codesum/config.py
codesum/file_utils.py
codesum/folder_utils.py
codesum/mcp_http_server.py
codesum/mcp_server.py
codesum/openai_utils.py
codesum/summary_utils.py
codesum/tui.py
codesum/prompts/system_readme.md
codesum/prompts/system_summary.md
codesum-0.3.1.dist-info/licenses/LICENSE
codesum-0.3.1.dist-info/METADATA
codesum-0.3.1.dist-info/WHEEL
codesum-0.3.1.dist-info/entry_points.txt
codesum-0.3.1.dist-info/top_level.txt
codesum-0.3.1.dist-info/RECORD
