Metadata-Version: 2.4
Name: codesum
Version: 0.3.1
Summary: Interactive code summarizer using AI and TUI
Author: Sam G
Keywords: code,summary,ai,openai,tui,curses,documentation
Classifier: Programming Language :: Python :: 3
Classifier: Operating System :: OS Independent
Classifier: Environment :: Console :: Curses
Classifier: Topic :: Software Development :: Documentation
Classifier: Topic :: Utilities
Requires-Python: >=3.8
License-File: LICENSE
Requires-Dist: openai
Requires-Dist: pathspec
Requires-Dist: python-dotenv
Requires-Dist: pyperclip
Requires-Dist: platformdirs>=4.0.0
Requires-Dist: tiktoken
Requires-Dist: windows-curses; sys_platform == "win32"
Requires-Dist: importlib-resources; python_version < "3.9"
Dynamic: license-file
